TBBS/__init__.py
TBBS/operations.py
TBBS-0.1.0.dist-info/LICENSE
TBBS-0.1.0.dist-info/METADATA
TBBS-0.1.0.dist-info/WHEEL
TBBS-0.1.0.dist-info/top_level.txt
TBBS-0.1.0.dist-info/RECORD
