Metadata-Version: 2.1
Name: TBBS
Version: 0.1.0
Summary: The TBBS Module
Home-page: https://github.com/yourusername/Slize
Author: Raghav and Ayush
Author-email: your.email@example.com
Classifier: Programming Language :: Python :: 3
Classifier: License :: OSI Approved :: MIT License
Classifier: Operating System :: OS Independent
Requires-Python: >=3.6
License-File: LICENSE
